setup.py
rons/__init__.py
rons/gens.py
rons/parse_url.py
rons/parser.py
rons/rons.py
rons/simplebuffer.py
rons.egg-info/PKG-INFO
rons.egg-info/SOURCES.txt
rons.egg-info/dependency_links.txt
rons.egg-info/top_level.txt
rons.egg-info/zip-safe