Metadata-Version: 1.0
Name: rons
Version: 0.0.1
Summary: RonS - simple pub/sub Redis client for Tornado
Home-page: http://github.com/majek/rons#readme
Author: Marek Majkowski
Author-email: rons@popcnt.org
License: MIT
Platform: any
